DrissionPage_expand/__init__.py
DrissionPage_expand/http_server.py
DrissionPage_expand/xhr_request.py
DrissionPage_expand-1.1.0.dist-info/LICENSE
DrissionPage_expand-1.1.0.dist-info/METADATA
DrissionPage_expand-1.1.0.dist-info/WHEEL
DrissionPage_expand-1.1.0.dist-info/top_level.txt
DrissionPage_expand-1.1.0.dist-info/RECORD
