Metadata-Version: 2.1
Name: DrissionPage-expand
Version: 1.1.0
Summary: DrissionPage扩展包，提供异步请求功能，通过HTTP服务器中转实现
Home-page: https://github.com/DrissionPage/DrissionPage-expand
Author: DrissionPage Expand
Author-email: drissionpage.expand@example.com
Project-URL: Bug Reports, https://github.com/DrissionPage/DrissionPage-expand/issues
Project-URL: Source, https://github.com/DrissionPage/DrissionPage-expand
Project-URL: Documentation, https://github.com/DrissionPage/DrissionPage-expand/blob/main/README.md
Keywords: drissionpage async request http automation web scraping
Classifier: Development Status :: 4 - Beta
Classifier: Intended Audience :: Developers
Classifier: Operating System :: OS Independent
Classifier: Programming Language :: Python :: 3
Classifier: Programming Language :: Python :: 3.7
Classifier: Programming Language :: Python :: 3.8
Classifier: Programming Language :: Python :: 3.9
Classifier: Programming Language :: Python :: 3.10
Classifier: Programming Language :: Python :: 3.11
Classifier: Programming Language :: Python :: 3.12
Classifier: Topic :: Internet :: WWW/HTTP
Classifier: Topic :: Software Development :: Libraries :: Python Modules
Classifier: Topic :: Software Development :: Testing
Requires-Python: >=3.7
License-File: LICENSE
Requires-Dist: Flask>=2.0.0
Requires-Dist: Flask-CORS>=3.0.0
Requires-Dist: DrissionPage>=4.0.0
